sphinx_docsearch/__init__.py
sphinx_docsearch/py.typed
sphinx_docsearch/static/alabaster-docsearch-custom.css
sphinx_docsearch/static/docsearch.css
sphinx_docsearch/static/docsearch.js
sphinx_docsearch/static/docsearch_config.js_t
sphinx_docsearch/static/furo-docsearch-custom.css
sphinx_docsearch/static/pydata-docsearch-custom.css
sphinx_docsearch/static/rtd-docsearch-custom.css
sphinx_docsearch/templates/searchbox.html
sphinx_docsearch/templates/searchfield.html
sphinx_docsearch/templates/sidebar/search.html
sphinx_docsearch-0.3.0.dist-info/METADATA
sphinx_docsearch-0.3.0.dist-info/WHEEL
sphinx_docsearch-0.3.0.dist-info/licenses/LICENSE
sphinx_docsearch-0.3.0.dist-info/RECORD
