Metadata-Version: 2.4
Name: sphinx-docsearch
Version: 0.3.0
Summary: A Sphinx extension for replacing the built-in search with Algolia DocSearch
Project-URL: homepage, https://sphinx-docsearch.readthedocs.io/
Project-URL: documentation, https://sphinx-docsearch.readthedocs.io/
Project-URL: repository, https://github.com/algolia/sphinx-docsearch
Project-URL: issues, https://github.com/algolia/sphinx-docsearch
Author-email: Algolia <support@algolia.com>
License-File: LICENSE
Classifier: Framework :: Sphinx
Classifier: Framework :: Sphinx :: Extension
Classifier: Programming Language :: Python
Classifier: Programming Language :: Python :: 3
Classifier: Programming Language :: Python :: 3.9
Classifier: Programming Language :: Python :: 3.10
Classifier: Programming Language :: Python :: 3.11
Classifier: Programming Language :: Python :: 3.12
Classifier: Programming Language :: Python :: 3.13
Classifier: Programming Language :: Python :: 3.14
Classifier: Topic :: Documentation
Classifier: Topic :: Documentation :: Sphinx
Classifier: Topic :: Software Development :: Documentation
Requires-Python: >=3.9
Requires-Dist: sphinx<10,>=7
